{
  
"Iklan": [
    {
      "pengaturan_iklan" : "1",
      "interval_intertitial": 2,
      
      "intertitial_admob":"ca-app-pub-6027254787204230/7116502065",
      "native_admob":"ca-app-pub-6027254787204230/9321167031",
     
      "status":"0",
      "link_redirect":"https://play.google.com/store/apps/details?id=com.ad.tesiqkepribadia&hl=en",

      "deskripsi_update":"Please update the application to the latest version to get additional features.",
      "version_json": 1,
      
      "startappid":"203285312",
    

      "fan_inter":"YOUR_PLACEMENT_ID",
      "fan_banner_native":"YOUR_PLACEMENT_ID",

      "more_app":"https://play.google.com/store/apps/dev?id=5673223097784726589",
       "hpk":"game,car,traveling,drawing"


    }
  ]
}
